openai_wrapper/__init__.py
openai_wrapper/config/__init__.py
openai_wrapper/config/logger.py
openai_wrapper/config/prompts.py
openai_wrapper/core/__init__.py
openai_wrapper/core/clients/__init__.py
openai_wrapper/core/clients/enhanced_openai_client.py
aichina_openai_wrapper-0.1.42.dist-info/METADATA
aichina_openai_wrapper-0.1.42.dist-info/WHEEL
aichina_openai_wrapper-0.1.42.dist-info/RECORD
