Metadata-Version: 2.1
Name: aichina-openai-wrapper
Version: 0.1.42
Summary: A wrapper for OpenAI utilities
Home-page: https://github.com/your-repo-url
License: MIT
Author: 杨烨
Author-email: imissyou5201314@outlook.com
Requires-Python: >=3.10,<4.0
Classifier: License :: OSI Approved :: MIT License
Classifier: Programming Language :: Python :: 3
Classifier: Programming Language :: Python :: 3.10
Classifier: Programming Language :: Python :: 3.11
Classifier: Programming Language :: Python :: 3.12
Classifier: Programming Language :: Python :: 3.13
Requires-Dist: openai (>=1.57.2,<2.0.0)
Requires-Dist: pytest (>=7.0.0,<8.0.0)
Project-URL: Repository, https://github.com/your-repo-url
